README.md
setup.py
grammalecte/README.txt
grammalecte/WARNING.txt
grammalecte/__init__.py
grammalecte/grammar_checker.py
grammalecte/text.py
grammalecte/fr/__init__.py
grammalecte/fr/conj.py
grammalecte/fr/conj_data.py
grammalecte/fr/cregex.py
grammalecte/fr/gc_engine.py
grammalecte/fr/gc_options.py
grammalecte/fr/gc_rules.py
grammalecte/fr/lexicographe.py
grammalecte/fr/locutions_data.py
grammalecte/fr/mfsp.py
grammalecte/fr/mfsp_data.py
grammalecte/fr/phonet.py
grammalecte/fr/phonet_data.py
grammalecte/fr/tests.py
grammalecte/fr/textformatter.py
grammalecte/graphspell/__init__.py
grammalecte/graphspell/char_player.py
grammalecte/graphspell/dawg.py
grammalecte/graphspell/echo.py
grammalecte/graphspell/ibdawg.py
grammalecte/graphspell/keyboard_chars_proximity.py
grammalecte/graphspell/progressbar.py
grammalecte/graphspell/spellchecker.py
grammalecte/graphspell/str_transform.py
grammalecte/graphspell/tokenizer.py
grammalecte/graphspell/_dictionaries/fr.bdic
konfiture/__init__.py
konfiture/grammar_checker.py
konfiture.egg-info/PKG-INFO
konfiture.egg-info/SOURCES.txt
konfiture.egg-info/dependency_links.txt
konfiture.egg-info/requires.txt
konfiture.egg-info/top_level.txt
scripts/konfiture