Metadata-Version: 1.0
Name: konfiture
Version: 0.3.0
Summary: Smart markdown grammar and spelling checker
Home-page: https://gitlab.com/konfiture/konfiture
Author: Noel Martignoni
Author-email: noel@martignoni.fr
License: GPL3
Platform: UNKNOWN
